financial_statement_parser/__init__.py
financial_statement_parser/cli.py
financial_statement_parser/config.py
financial_statement_parser/parser.py
financial_statement_parser-0.1.4.dist-info/LICENSE.txt
financial_statement_parser-0.1.4.dist-info/METADATA
financial_statement_parser-0.1.4.dist-info/WHEEL
financial_statement_parser-0.1.4.dist-info/entry_points.txt
financial_statement_parser-0.1.4.dist-info/RECORD
