Metadata-Version: 2.1
Name: financial-statement-parser
Version: 0.1.4
Summary: 
Author: Xavier Armitage
Author-email: xavier.armitage@databricks.com
Requires-Python: >=3.11,<4.0
Classifier: Programming Language :: Python :: 3
Classifier: Programming Language :: Python :: 3.11
Classifier: Programming Language :: Python :: 3.12
Requires-Dist: pytz (>=2024.1,<2025.0)
